plugins/__init__.py
metadata_registry_interface_specifications-0.3.3.dist-info/LICENSE
metadata_registry_interface_specifications-0.3.3.dist-info/METADATA
metadata_registry_interface_specifications-0.3.3.dist-info/WHEEL
metadata_registry_interface_specifications-0.3.3.dist-info/top_level.txt
metadata_registry_interface_specifications-0.3.3.dist-info/RECORD
