Metadata-Version: 2.1
Name: metadata-registry-interface-specifications
Version: 0.3.3
Summary: Metadata Registry interface specifications
Home-page: https://github.com/jacbeekers/metadata-registry-interface-specifications
Author: Jac. Beekers
Author-email: beekersjac@gmail.com
License: UNKNOWN
Platform: UNKNOWN
Classifier: Programming Language :: Python :: 3
Classifier: License :: OSI Approved :: MIT License
Classifier: Operating System :: OS Independent
Requires-Python: >=3.6
Requires-Dist: jsonschema
